MANIFEST.in
README
setup.py
oldowan/__init__.py
oldowan.mtconvert.egg-info/PKG-INFO
oldowan.mtconvert.egg-info/SOURCES.txt
oldowan.mtconvert.egg-info/dependency_links.txt
oldowan.mtconvert.egg-info/namespace_packages.txt
oldowan.mtconvert.egg-info/not-zip-safe
oldowan.mtconvert.egg-info/requires.txt
oldowan.mtconvert.egg-info/top_level.txt
oldowan/mtconvert/VERSION
oldowan/mtconvert/__init__.py
oldowan/mtconvert/find_range.py
oldowan/mtconvert/mitomap_data.py
oldowan/mtconvert/reduction_funcs.py
oldowan/mtconvert/seq2sites.py
oldowan/mtconvert/sites2seq.py
oldowan/mtconvert/sites2str.py
oldowan/mtconvert/str2sites.py
oldowan/mtconvert/biopython/__init__.py
oldowan/mtconvert/biopython/listfns.py
oldowan/mtconvert/biopython/pairwise2.py